smact/__init__.py
smact/builder.py
smact/data_loader.py
smact/distorter.py
smact/lattice.py
smact/lattice_parameters.py
smact/mainpage.py
smact/metallicity.py
smact/oxidation_states.py
smact/properties.py
smact/screening.py
smact/benchmarking/__init__.py
smact/benchmarking/pymatgen_benchmark.py
smact/benchmarking/smact_benchmark.py
smact/benchmarking/utilities.py
smact/data/Covalent_radii.csv
smact/data/SSE.csv
smact/data/SSE_2015.csv
smact/data/SSE_Pauling.csv
smact/data/element_data.txt
smact/data/element_valence_modified.csv
smact/data/hhi.txt
smact/data/ionic_radii.csv
smact/data/magpie.csv
smact/data/ordered_periodic.txt
smact/data/oxidation_state_probability_table.json
smact/data/oxidation_states.txt
smact/data/oxidation_states_SP.txt
smact/data/oxidation_states_icsd.txt
smact/data/oxidation_states_icsd24_common.txt
smact/data/oxidation_states_icsd24_counts.json
smact/data/oxidation_states_icsd24_filtered.txt
smact/data/oxidation_states_icsd24_raw.txt
smact/data/oxidation_states_pmg.txt
smact/data/oxidation_states_wiki.txt
smact/data/shannon_radii.csv
smact/data/shannon_radii_ML_extended.csv
smact/data/solid_properties.txt
smact/data/solid_properties.xlsx
smact/data/species_rep/ion_embedding_M3GNet-MP-2023.11.1-oxi-Eform_cosine_similarity.json
smact/data/species_rep/ion_embedding_M3GNet-MP-2023.11.1-oxi-band_gap_cosine_similarity.json
smact/data/species_rep/skipspecies_20221028_319ion_dim200_cosine_similarity.json
smact/dopant_prediction/__init__.py
smact/dopant_prediction/doper.py
smact/structure_prediction/__init__.py
smact/structure_prediction/database.py
smact/structure_prediction/mutation.py
smact/structure_prediction/prediction.py
smact/structure_prediction/probability_models.py
smact/structure_prediction/structure.py
smact/structure_prediction/utilities.py
smact/tests/__init__.py
smact/tests/test_core.py
smact/tests/test_doper.py
smact/tests/test_metallicity.py
smact/tests/test_structure.py
smact/tests/test_utils.py
smact/utils/__init__.py
smact-3.2.0.dist-info/licenses/LICENSE
smact-3.2.0.dist-info/METADATA
smact-3.2.0.dist-info/WHEEL
smact-3.2.0.dist-info/top_level.txt
smact-3.2.0.dist-info/RECORD
