Metadata-Version: 2.4
Name: SMACT
Version: 3.2.0
Summary: Semiconducting Materials by Analogy and Chemical Theory
Author-email: The SMACT Developers <a.walsh@imperial.ac.uk>
Maintainer-email: "Anthony O. Onwuli" <anthony.onwuli16@imperial.ac.uk>
License-Expression: MIT
Project-URL: Homepage, https://github.com/WMD-group/SMACT
Project-URL: Documentation, https://smact.readthedocs.io/en/latest/
Project-URL: Repository, https://github.com/WMD-group/SMACT
Project-URL: Issues, https://github.com/WMD-group/SMACT/issues
Project-URL: Pypi, https://pypi.org/project/SMACT/
Keywords: python,machine-learning,computational-chemistry,materials-science,materials-informatics,materials-screening,materials-design,materials
Classifier: Development Status :: 5 - Production/Stable
Classifier: Intended Audience :: Science/Research
Classifier: Operating System :: OS Independent
Classifier: Programming Language :: Python :: 3
Classifier: Programming Language :: Python :: 3.10
Classifier: Programming Language :: Python :: 3.11
Classifier: Programming Language :: Python :: 3.12
Classifier: Programming Language :: Python :: 3.13
Classifier: Topic :: Scientific/Engineering
Classifier: Topic :: Scientific/Engineering :: Chemistry
Requires-Python: <3.14,>=3.10
License-File: LICENSE
Requires-Dist: ase
Requires-Dist: numpy<3
Requires-Dist: pandarallel[optional]>=1.6.5
Requires-Dist: pandas
Requires-Dist: pathos
Requires-Dist: pymatgen>=2024.2.20
Requires-Dist: scipy
Requires-Dist: spglib>=2.6.0
Requires-Dist: typing-extensions
Provides-Extra: dev
Requires-Dist: pytest; extra == "dev"
Requires-Dist: ruff; extra == "dev"
Requires-Dist: pyright; extra == "dev"
Requires-Dist: codespell; extra == "dev"
Requires-Dist: pytest-cov; extra == "dev"
Requires-Dist: blacken-docs; extra == "dev"
Requires-Dist: nbstripout; extra == "dev"
Provides-Extra: docs
Requires-Dist: sphinx==8.1.3; extra == "docs"
Requires-Dist: sphinx_rtd_theme==3.0.2; extra == "docs"
Requires-Dist: readthedocs-sphinx-search==0.3.2; extra == "docs"
Requires-Dist: sphinx-book-theme==1.1.3; extra == "docs"
Requires-Dist: myst-nb==1.1.2; extra == "docs"
Provides-Extra: mp
Requires-Dist: mp-api>=0.45.3; extra == "mp"
Provides-Extra: crystal-space
Requires-Dist: smact[mp]; extra == "crystal-space"
Requires-Dist: ElementEmbeddings>=0.4; extra == "crystal-space"
Requires-Dist: umap-learn==0.5.7; extra == "crystal-space"
Requires-Dist: kaleido>=0.2.1; extra == "crystal-space"
Provides-Extra: featurisers
Requires-Dist: matminer; extra == "featurisers"
Requires-Dist: ElementEmbeddings; extra == "featurisers"
Provides-Extra: visualisation
Requires-Dist: seaborn>=0.13.2; extra == "visualisation"
Requires-Dist: pymatviz>=0.15; extra == "visualisation"
Requires-Dist: dash>=2.18.2; extra == "visualisation"
Provides-Extra: ml
Requires-Dist: xgboost; extra == "ml"
Requires-Dist: shap; extra == "ml"
Requires-Dist: smact[featurisers]; extra == "ml"
Provides-Extra: optional
Requires-Dist: pydantic>=2.9.2; extra == "optional"
Requires-Dist: smact[mp]; extra == "optional"
Requires-Dist: smact[visualisation]; extra == "optional"
Requires-Dist: pymatgen>=2024.2.20; extra == "optional"
Requires-Dist: matminer>=0.9.2; extra == "optional"
Requires-Dist: kaleido>=0.2.1; extra == "optional"
Requires-Dist: ase>=3.22.0; extra == "optional"
Requires-Dist: llvmlite>=0.40; extra == "optional"
Requires-Dist: ElementEmbeddings>=0.4; extra == "optional"
Requires-Dist: dash>=2.18.2; extra == "optional"
Requires-Dist: smact[ml]; extra == "optional"
Requires-Dist: pandarallel>=1.6.5; extra == "optional"
Requires-Dist: matplotlib-venn[shapely]>=1.1.2; extra == "optional"
Provides-Extra: strict
Requires-Dist: pydantic==2.9.2; extra == "strict"
Requires-Dist: mp-api==0.45.5; extra == "strict"
Requires-Dist: pymatviz==0.15.1; extra == "strict"
Requires-Dist: mp-api==0.45.5; extra == "strict"
Requires-Dist: seaborn==0.13.2; extra == "strict"
Requires-Dist: pymatgen==2025.4.24; extra == "strict"
Requires-Dist: matminer==0.9.3; extra == "strict"
Requires-Dist: umap-learn==0.5.7; extra == "strict"
Requires-Dist: kaleido==0.2.1; extra == "strict"
Requires-Dist: ase==3.24.0; extra == "strict"
Requires-Dist: numpy; extra == "strict"
Requires-Dist: ElementEmbeddings==0.6.1; extra == "strict"
Requires-Dist: dash==3.0.2; extra == "strict"
Dynamic: license-file
